CHANGES.rst
MANIFEST.in
README.rst
setup.py
python_tr.egg-info/PKG-INFO
python_tr.egg-info/SOURCES.txt
python_tr.egg-info/dependency_links.txt
python_tr.egg-info/top_level.txt
tr/__init__.py
tr/compat.py
tr/tr.py