Metadata-Version: 1.1
Name: python-tr
Version: 0.1.1
Summary: A Pure-Python implementation of the tr algorithm
Home-page: https://github.com/ikegami-yukino/python-tr
Author: Yukino Ikegami
Author-email: yukino0131@me.com
License: MIT License
Keywords: tr,transliterate,translate
Platform: POSIX
Platform: Windows
Platform: Unix
Platform: MacOS
Classifier: Development Status :: 4 - Beta
Classifier: Intended Audience :: Developers
Classifier: Intended Audience :: Information Technology
Classifier: License :: OSI Approved :: MIT License
Classifier: Operating System :: MacOS
Classifier: Operating System :: Microsoft
Classifier: Operating System :: POSIX
Classifier: Programming Language :: Python :: 2.6
Classifier: Programming Language :: Python :: 2.7
Classifier: Programming Language :: Python :: 3.3
Classifier: Programming Language :: Python :: 3.4
Classifier: Topic :: Text Processing :: General
